{
  "hsk1": [
    {
      "id": 1,
      "hanzi": "爱",
      "pinyin": "ài",
      "significado": "amar · tener afecto",
      "audio": "assets/audios/1. 爱",
      "trazo": "https://www.strokeorder.com/assets/bishun/animation/29233.gif"
    },
    {
      "id": 2,
      "hanzi": "八",
      "pinyin": "bā",
      "significado": "ocho",
      "audio": "assets/audios/2. 八",
      "trazo": "https://www.strokeorder.com/assets/bishun/animation/20843.gif"
    },
    {
      "id": 3,
      "hanzi": "爸爸",
      "pinyin": "bà ba",
      "significado": "papá",
      "audio": "assets/audios/3. 爸爸",
      "trazo": "https://www.strokeorder.com/assets/bishun/animation/29240.gif"
    },
    {
      "id": 4,
      "hanzi": "杯子",
      "pinyin": "bēi zi",
      "significado": "taza · vaso",
      "audio": "assets/audios/4. 杯子",
      "trazo": "https://www.strokeorder.com/assets/bishun/animation/26479.gif",
      "trazo2": "https://www.strokeorder.com/assets/bishun/animation/23376.gif"
    },
    {
      "id": 5,
      "hanzi": "北京",
      "pinyin": "běi jīng",
      "significado": "Beijing",
      "audio": "assets/audios/5. 北京",
      "trazo": "https://www.strokeorder.com/assets/bishun/animation/21271.gif",
      "trazo2": "https://www.strokeorder.com/assets/bishun/animation/20140.gif"
    },
    {
      "id": 6,
      "hanzi": "本",
      "pinyin": "běn",
      "significado": "cuaderno · raiz · origen · clasificador para libros",
      "audio": "assets/audios/6. 本",
      "trazo": "https://www.strokeorder.com/assets/bishun/animation/26412.gif"
    },
    {
      "id": 7,
      "hanzi": "不客气",
      "pinyin": "bú kè qi",
      "significado": "de nada",
      "audio": "assets/audios/7. 不客气",
      "trazo": "https://www.strokeorder.com/assets/bishun/animation/19981.gif",
      "trazo2": "https://www.strokeorder.com/assets/bishun/animation/23458.gif",
      "trazo3": "https://www.strokeorder.com/assets/bishun/animation/27668.gif"
    },
    {
      "id": 8,
      "hanzi": "不",
      "pinyin": "bù",
      "significado": "no",
      "audio": "assets/audios/8. 不",
      "trazo": "https://www.strokeorder.com/assets/bishun/animation/19981.gif"
    },
    {
      "id": 9,
      "hanzi": "菜",
      "pinyin": "cài",
      "significado": "verduras · plato (de comida)",
      "audio": "assets/audios/9. 菜",
      "trazo": "https://www.strokeorder.com/assets/bishun/animation/33756.gif"
    },
    {
      "id": 10,
      "hanzi": "茶",
      "pinyin": "chá",
      "significado": "té",
      "audio": "assets/audios/10. 茶",
      "trazo": "https://www.strokeorder.com/assets/bishun/animation/33590.gif"
    },
    {
      "id": 11,
      "hanzi": "吃",
      "pinyin": "chī",
      "significado": "comer",
      "audio": "assets/audios/11.吃",
      "trazo": "https://www.strokeorder.com/assets/bishun/animation/21507.gif"
    },
    {
      "id": 12,
      "hanzi": "出租车",
      "pinyin": "chū zū chē",
      "significado": "taxi",
      "audio": "assets/audios/12.出租车",
      "trazo": "https://www.strokeorder.com/assets/bishun/animation/20986.gif",
      "trazo2": "https://www.strokeorder.com/assets/bishun/animation/31199.gif",
      "trazo3": "https://www.strokeorder.com/assets/bishun/animation/36710.gif"
    },
    {
      "id": 13,
      "hanzi": "打电话",
      "pinyin": "dǎ diàn huà",
      "significado": "llamar por teléfono",
      "audio": "assets/audios/13.打电话",
      "trazo": "https://www.strokeorder.com/assets/bishun/animation/25171.gif",
      "trazo2": "https://www.strokeorder.com/assets/bishun/animation/30005.gif",
      "trazo3": "https://www.strokeorder.com/assets/bishun/animation/35805.gif"
    },
    {
      "id": 14,
      "hanzi": "大",
      "pinyin": "dà",
      "significado": "grande",
      "audio": "assets/audios/14.大",
      "trazo": "https://www.strokeorder.com/assets/bishun/animation/22823.gif"
    },
    {
      "id": 15,
      "hanzi": "的",
      "pinyin": "de",
      "significado": "partícula estructural · delante de un sustantivo indica posesión o atributo descriptivo",
      "audio": "assets/audios/15.的",
      "trazo": "https://www.strokeorder.com/assets/bishun/animation/30340.gif"
    },
    {
      "id": 16,
      "hanzi": "点",
      "pinyin": "diǎn",
      "significado": "hora en punto · pequeña cantidad",
      "audio": "assets/audios/16.点",
      "trazo": "https://www.strokeorder.com/assets/bishun/animation/28857.gif"
    },
    {
      "id": 17,
      "hanzi": "电脑",
      "pinyin": "diàn nǎo",
      "significado": "ordenador",
      "audio": "assets/audios/17.电脑",
      "trazo": "https://www.strokeorder.com/assets/bishun/animation/30005.gif",
      "trazo2": "https://www.strokeorder.com/assets/bishun/animation/33041.gif"
    },
    {
      "id": 18,
      "hanzi": "电视",
      "pinyin": "diàn shì",
      "significado": "televisión",
      "audio": "assets/audios/18.电视",
      "trazo": "https://www.strokeorder.com/assets/bishun/animation/30005.gif",
      "trazo2": "https://www.strokeorder.com/assets/bishun/animation/35270.gif"
    },
    {
      "id": 19,
      "hanzi": "电影",
      "pinyin": "diàn yǐng",
      "significado": "película de cine",
      "audio": "assets/audios/19.电影",
      "trazo": "https://www.strokeorder.com/assets/bishun/animation/30005.gif",
      "trazo2": "https://www.strokeorder.com/assets/bishun/animation/24433.gif"
    },
    {
      "id": 20,
      "hanzi": "东西",
      "pinyin": "dōng xi",
      "significado": "cosa",
      "audio": "assets/audios/20.东西",
      "trazo": "https://www.strokeorder.com/assets/bishun/animation/19996.gif",
      "trazo2": "https://www.strokeorder.com/assets/bishun/animation/35199.gif"
    },
    {
      "id": 21,
      "hanzi": "都",
      "pinyin": "dōu",
      "significado": "todo · todos",
      "audio": "assets/audios/21.都",
      "trazo": "https://www.strokeorder.com/assets/bishun/animation/37117.gif"
    },
    {
      "id": 22,
      "hanzi": "读",
      "pinyin": "dú",
      "significado": "leer · estudiar",
      "audio": "assets/audios/22.读",
      "trazo": "https://www.strokeorder.com/assets/bishun/animation/35835.gif"
    },
    {
      "id": 23,
      "hanzi": "对不起",
      "pinyin": "duì bu qǐ",
      "significado": "lo siento · disculpa",
      "audio": "assets/audios/23.对不起",
      "trazo": "https://www.strokeorder.com/assets/bishun/animation/23545.gif",
      "trazo2": "https://www.strokeorder.com/assets/bishun/animation/19981.gif",
      "trazo3": "https://www.strokeorder.com/assets/bishun/animation/36215.gif"
    },
    {
      "id": 24,
      "hanzi": "多",
      "pinyin": "duō",
      "significado": "mucho",
      "audio": "assets/audios/24.多",
      "trazo": "https://www.strokeorder.com/assets/bishun/animation/22810.gif"
    },
    {
      "id": 25,
      "hanzi": "多少",
      "pinyin": "duō shǎo",
      "significado": "¿cuánto? · ¿cuántos?",
      "audio": "assets/audios/25.多少",
      "trazo": "https://www.strokeorder.com/assets/bishun/animation/22810.gif",
      "trazo2": "https://www.strokeorder.com/assets/bishun/animation/23569.gif"
    },
    {
      "id": 26,
      "hanzi": "儿子",
      "pinyin": "ér zi",
      "significado": "hijo",
      "audio": "assets/audios/26.儿子",
      "trazo": "https://www.strokeorder.com/assets/bishun/animation/20799.gif",
      "trazo2": "https://www.strokeorder.com/assets/bishun/animation/23376.gif"
    },
    {
      "id": 27,
      "hanzi": "二",
      "pinyin": "èr",
      "significado": "dos · 2",
      "audio": "assets/audios/27.二",
      "trazo": "https://www.strokeorder.com/assets/bishun/animation/20108.gif"
    },
    {
      "id": 28,
      "hanzi": "饭店",
      "pinyin": "fàn diàn",
      "significado": "restaurante · hotel",
      "audio": "assets/audios/28.饭店",
      "trazo": "https://www.strokeorder.com/assets/bishun/animation/39277.gif",
      "trazo2": "https://www.strokeorder.com/assets/bishun/animation/24215.gif"
    },
    {
      "id": 29,
      "hanzi": "飞机",
      "pinyin": "fēi jī",
      "significado": "avión",
      "audio": "assets/audios/29.飞机",
      "trazo": "https://www.strokeorder.com/assets/bishun/animation/39134.gif",
      "trazo2": "https://www.strokeorder.com/assets/bishun/animation/26426.gif"
    },
    {
      "id": 30,
      "hanzi": "分钟",
      "pinyin": "fēn zhōng",
      "significado": "minuto",
      "audio": "assets/audios/30.分钟",
      "trazo": "https://www.strokeorder.com/assets/bishun/animation/20998.gif",
      "trazo2": "https://www.strokeorder.com/assets/bishun/animation/38047.gif"
    },
    {
      "id": 31,
      "hanzi": "高兴",
      "pinyin": "gāo xìng",
      "significado": "contento",
      "audio": "assets/audios/31.高兴",
      "trazo": "https://www.strokeorder.com/assets/bishun/animation/39640.gif",
      "trazo2": "https://www.strokeorder.com/assets/bishun/animation/20852.gif"
    },
    {
      "id": 32,
      "hanzi": "个",
      "pinyin": "gè",
      "significado": "clasificador general para personas y objetos en general",
      "audio": "assets/audios/32.个",
      "trazo": "https://www.strokeorder.com/assets/bishun/animation/20010.gif"
    },
    {
      "id": 33,
      "hanzi": "工作",
      "pinyin": "gōng zuò",
      "significado": "trabajo",
      "audio": "assets/audios/33.工作",
      "trazo": "https://www.strokeorder.com/assets/bishun/animation/24037.gif",
      "trazo2": "https://www.strokeorder.com/assets/bishun/animation/20316.gif"
    },
    {
      "id": 34,
      "hanzi": "狗",
      "pinyin": "gǒu",
      "significado": "perro",
      "audio": "assets/audios/34.狗",
      "trazo": "https://www.strokeorder.com/assets/bishun/animation/29399.gif"
    },
    {
      "id": 35,
      "hanzi": "汉语",
      "pinyin": "hàn yǔ",
      "significado": "lengua china",
      "audio": "assets/audios/35.汉语",
      "trazo": "https://www.strokeorder.com/assets/bishun/animation/27721.gif",
      "trazo2": "https://www.strokeorder.com/assets/bishun/animation/35821.gif"
    },
    {
      "id": 36,
      "hanzi": "好",
      "pinyin": "hǎo",
      "significado": "bien · bueno",
      "audio": "assets/audios/36.好",
      "trazo": "https://www.strokeorder.com/assets/bishun/animation/22909.gif"
    },
    {
      "id": 37,
      "hanzi": "号",
      "pinyin": "hào",
      "significado": "número · día del mes",
      "audio": "assets/audios/37.号",
      "trazo": "https://www.strokeorder.com/assets/bishun/animation/21495.gif"
    },
    {
      "id": 38,
      "hanzi": "喝",
      "pinyin": "hē",
      "significado": "beber",
      "audio": "assets/audios/38.喝",
      "trazo": "https://www.strokeorder.com/assets/bishun/animation/21917.gif"
    },
    {
      "id": 39,
      "hanzi": "和",
      "pinyin": "hé",
      "significado": "y",
      "audio": "assets/audios/39.和",
      "trazo": "https://www.strokeorder.com/assets/bishun/animation/21644.gif"
    },
    {
      "id": 40,
      "hanzi": "很",
      "pinyin": "hěn",
      "significado": "muy",
      "audio": "assets/audios/40.很",
      "trazo": "https://www.strokeorder.com/assets/bishun/animation/24456.gif"
    },
    {
      "id": 41,
      "hanzi": "后面",
      "pinyin": "hòu miàn",
      "significado": "detrás",
      "audio": "assets/audios/41.后面",
      "trazo": "https://www.strokeorder.com/assets/bishun/animation/21518.gif",
      "trazo2": "https://www.strokeorder.com/assets/bishun/animation/38754.gif"
    },
    {
      "id": 42,
      "hanzi": "回",
      "pinyin": "huí",
      "significado": "volver",
      "audio": "assets/audios/42.回",
      "trazo": "https://www.strokeorder.com/assets/bishun/animation/22238.gif"
    },
    {
      "id": 43,
      "hanzi": "会",
      "pinyin": "huì",
      "significado": "tener la habilidad de",
      "audio": "assets/audios/43.会",
      "trazo": "https://www.strokeorder.com/assets/bishun/animation/20250.gif"
    },
    {
      "id": 44,
      "hanzi": "几",
      "pinyin": "jǐ",
      "significado": "unos pocos · unos cuantos · cuántos",
      "audio": "assets/audios/44.几",
      "trazo": "https://www.strokeorder.com/assets/bishun/animation/20960.gif"
    },
    {
      "id": 45,
      "hanzi": "家",
      "pinyin": "jiā",
      "significado": "hogar · familia",
      "audio": "assets/audios/45.家",
      "trazo": "https://www.strokeorder.com/assets/bishun/animation/23478.gif"
    },
    {
      "id": 46,
      "hanzi": "叫",
      "pinyin": "jiào",
      "significado": "llamarse",
      "audio": "assets/audios/46.叫",
      "trazo": "https://www.strokeorder.com/assets/bishun/animation/21483.gif"
    },
    {
      "id": 47,
      "hanzi": "今天",
      "pinyin": "jīn tiān",
      "significado": "hoy",
      "audio": "assets/audios/47.今天",
      "trazo": "https://www.strokeorder.com/assets/bishun/animation/20170.gif",
      "trazo2": "https://www.strokeorder.com/assets/bishun/animation/22825.gif"
    },
    {
      "id": 48,
      "hanzi": "九",
      "pinyin": "jiǔ",
      "significado": "nueve · 9",
      "audio": "assets/audios/48.九",
      "trazo": "https://www.strokeorder.com/assets/bishun/animation/20061.gif"
    },
    {
      "id": 49,
      "hanzi": "开",
      "pinyin": "kāi",
      "significado": "abrir · empezar · conducir",
      "audio": "assets/audios/49.开",
      "trazo": "https://www.strokeorder.com/assets/bishun/animation/24320.gif"
    },
    {
      "id": 50,
      "hanzi": "看",
      "pinyin": "kàn",
      "significado": "ver · mirar · leer",
      "audio": "assets/audios/50.看",
      "trazo": "https://www.strokeorder.com/assets/bishun/animation/30475.gif"
    },
    {
      "id": 51,
      "hanzi": "看见",
      "pinyin": "kàn jiàn",
      "significado": "mirar",
      "audio": "assets/audios/51.看见",
      "trazo": "https://www.strokeorder.com/assets/bishun/animation/30475.gif",
      "trazo2": "https://www.strokeorder.com/assets/bishun/animation/35265.gif"
    },
    {
      "id": 52,
      "hanzi": "块",
      "pinyin": "kuài",
      "significado": "pedazo · CL: piezas de ropa · CL: para dinero y unidades monetarias",
      "audio": "assets/audios/52.块",
      "trazo": "https://www.strokeorder.com/assets/bishun/animation/22359.gif"
    },
    {
      "id": 53,
      "hanzi": "来",
      "pinyin": "lái",
      "significado": "venir",
      "audio": "assets/audios/53.来",
      "trazo": "https://www.strokeorder.com/assets/bishun/animation/26469.gif"
    },
    {
      "id": 54,
      "hanzi": "老师",
      "pinyin": "lǎo shī",
      "significado": "profesor",
      "audio": "assets/audios/54.老师",
      "trazo": "https://www.strokeorder.com/assets/bishun/animation/32769.gif",
      "trazo2": "https://www.strokeorder.com/assets/bishun/animation/24072.gif"
    },
    {
      "id": 55,
      "hanzi": "了",
      "pinyin": "le",
      "significado": "partícula modal, intensifica acción previa, indica cambio o acción completada",
      "audio": "assets/audios/55.了",
      "trazo": "https://www.strokeorder.com/assets/bishun/animation/20102.gif"
    },
    {
      "id": 56,
      "hanzi": "冷",
      "pinyin": "lěng",
      "significado": "frío",
      "audio": "assets/audios/56.冷",
      "trazo": "https://www.strokeorder.com/assets/bishun/animation/20919.gif"
    },
    {
      "id": 57,
      "hanzi": "里",
      "pinyin": "lǐ",
      "significado": "dentro",
      "audio": "assets/audios/57.里",
      "trazo": "https://www.strokeorder.com/assets/bishun/animation/37324.gif"
    },
    {
      "id": 58,
      "hanzi": "六",
      "pinyin": "liù",
      "significado": "seis · 6",
      "audio": "assets/audios/58.六",
      "trazo": "https://www.strokeorder.com/assets/bishun/animation/20845.gif"
    },
    {
      "id": 59,
      "hanzi": "吗",
      "pinyin": "ma",
      "significado": "partícula para preguntas · utilizada al final de una pregunta",
      "audio": "assets/audios/59.吗",
      "trazo": "https://www.strokeorder.com/assets/bishun/animation/21527.gif"
    },
    {
      "id": 60,
      "hanzi": "妈妈",
      "pinyin": "mā ma",
      "significado": "mamá",
      "audio": "assets/audios/60.妈妈",
      "trazo": "https://www.strokeorder.com/assets/bishun/animation/22920.gif"
    },
    {
      "id": 61,
      "hanzi": "买",
      "pinyin": "mǎi",
      "significado": "comprar",
      "audio": "assets/audios/61.买",
      "trazo": "https://www.strokeorder.com/assets/bishun/animation/20080.gif"
    },
    {
      "id": 62,
      "hanzi": "猫",
      "pinyin": "māo",
      "significado": "gato",
      "audio": "assets/audios/62.猫",
      "trazo": "https://www.strokeorder.com/assets/bishun/animation/29483.gif"
    },
    {
      "id": 63,
      "hanzi": "没关系",
      "pinyin": "méi guān xi",
      "significado": "no tiene importancia",
      "audio": "assets/audios/63.没关系",
      "trazo": "https://www.strokeorder.com/assets/bishun/animation/27809.gif",
      "trazo2": "https://www.strokeorder.com/assets/bishun/animation/20851.gif",
      "trazo3": "https://www.strokeorder.com/assets/bishun/animation/31995.gif"
    },
    {
      "id": 64,
      "hanzi": "没有",
      "pinyin": "méi yǒu",
      "significado": "no tener · no existir · a no ser",
      "audio": "assets/audios/64.没有",
      "trazo": "https://www.strokeorder.com/assets/bishun/animation/27809.gif",
      "trazo2": "https://www.strokeorder.com/assets/bishun/animation/26377.gif"
    },
    {
      "id": 65,
      "hanzi": "米饭",
      "pinyin": "mǐ fàn",
      "significado": "arroz cocido",
      "audio": "assets/audios/65.米饭",
      "trazo": "https://www.strokeorder.com/assets/bishun/animation/31859.gif",
      "trazo2": "https://www.strokeorder.com/assets/bishun/animation/39277.gif"
    },
    {
      "id": 66,
      "hanzi": "名字",
      "pinyin": "míng zi",
      "significado": "nombre",
      "audio": "assets/audios/66.名字",
      "trazo": "https://www.strokeorder.com/assets/bishun/animation/21517.gif",
      "trazo2": "https://www.strokeorder.com/assets/bishun/animation/23383.gif"
    },
    {
      "id": 67,
      "hanzi": "明天",
      "pinyin": "míng tiān",
      "significado": "mañana",
      "audio": "assets/audios/67.明天",
      "trazo": "https://www.strokeorder.com/assets/bishun/animation/26126.gif",
      "trazo2": "https://www.strokeorder.com/assets/bishun/animation/22825.gif"
    },
    {
      "id": 68,
      "hanzi": "哪",
      "pinyin": "nǎ",
      "significado": "cuál",
      "audio": "assets/audios/68.哪",
      "trazo": "https://www.strokeorder.com/assets/bishun/animation/21738.gif"
    },
    {
      "id": 69,
      "hanzi": "哪儿",
      "pinyin": "nǎ er",
      "significado": "¿dónde?",
      "audio": "assets/audios/69.哪儿",
      "trazo": "https://www.strokeorder.com/assets/bishun/animation/21738.gif",
      "trazo2": "https://www.strokeorder.com/assets/bishun/animation/20799.gif"
    },
    {
      "id": 70,
      "hanzi": "那",
      "pinyin": "nà",
      "significado": "aquel",
      "audio": "assets/audios/70.那",
      "trazo": "https://www.strokeorder.com/assets/bishun/animation/37027.gif"
    },
    {
      "id": 71,
      "hanzi": "呢",
      "pinyin": "ne",
      "significado": "partícula para preguntar sobre opinión, ubicación, afirmación, etc",
      "audio": "assets/audios/71.呢",
      "trazo": "https://www.strokeorder.com/assets/bishun/animation/21602.gif"
    },
    {
      "id": 72,
      "hanzi": "能",
      "pinyin": "néng",
      "significado": "poder · tener la capacidad de",
      "audio": "assets/audios/72.能",
      "trazo": "https://www.strokeorder.com/assets/bishun/animation/33021.gif"
    },
    {
      "id": 73,
      "hanzi": "你",
      "pinyin": "nǐ",
      "significado": "tú",
      "audio": "assets/audios/73.你",
      "trazo": "https://www.strokeorder.com/assets/bishun/animation/20320.gif"
    },
    {
      "id": 74,
      "hanzi": "年",
      "pinyin": "nián",
      "significado": "año",
      "audio": "assets/audios/74.年",
      "trazo": "https://www.strokeorder.com/assets/bishun/animation/24180.gif"
    },
    {
      "id": 75,
      "hanzi": "女儿",
      "pinyin": "nǚ ér",
      "significado": "hija",
      "audio": "assets/audios/75.女儿",
      "trazo": "https://www.strokeorder.com/assets/bishun/animation/22899.gif",
      "trazo2": "https://www.strokeorder.com/assets/bishun/animation/20799.gif"
    },
    {
      "id": 76,
      "hanzi": "朋友",
      "pinyin": "péng you",
      "significado": "amigo",
      "audio": "assets/audios/76.朋友",
      "trazo": "https://www.strokeorder.com/assets/bishun/animation/26379.gif",
      "trazo2": "https://www.strokeorder.com/assets/bishun/animation/21451.gif"
    },
    {
      "id": 77,
      "hanzi": "漂亮",
      "pinyin": "piào liang",
      "significado": "bonito",
      "audio": "assets/audios/77.漂亮",
      "trazo": "https://www.strokeorder.com/assets/bishun/animation/28418.gif",
      "trazo2": "https://www.strokeorder.com/assets/bishun/animation/20142.gif"
    },
    {
      "id": 78,
      "hanzi": "苹果",
      "pinyin": "píng guǒ",
      "significado": "manzana",
      "audio": "assets/audios/78.苹果",
      "trazo": "https://www.strokeorder.com/assets/bishun/animation/33529.gif",
      "trazo2": "https://www.strokeorder.com/assets/bishun/animation/26524.gif"
    },
    {
      "id": 79,
      "hanzi": "七",
      "pinyin": "qī",
      "significado": "siete · 7",
      "audio": "assets/audios/79.七",
      "trazo": "https://www.strokeorder.com/assets/bishun/animation/19971.gif"
    },
    {
      "id": 80,
      "hanzi": "前面",
      "pinyin": "qián miàn",
      "significado": "en frente · delante de",
      "audio": "assets/audios/80.前面",
      "trazo": "https://www.strokeorder.com/assets/bishun/animation/21069.gif",
      "trazo2": "https://www.strokeorder.com/assets/bishun/animation/38754.gif"
    },
    {
      "id": 81,
      "hanzi": "钱",
      "pinyin": "qián",
      "significado": "dinero",
      "audio": "assets/audios/81.钱",
      "trazo": "https://www.strokeorder.com/assets/bishun/animation/38065.gif"
    },
    {
      "id": 82,
      "hanzi": "请",
      "pinyin": "qǐng",
      "significado": "iniciar pregunta o invitación para realizar algo",
      "audio": "assets/audios/82.请",
      "trazo": "https://www.strokeorder.com/assets/bishun/animation/35831.gif"
    },
    {
      "id": 83,
      "hanzi": "去",
      "pinyin": "qù",
      "significado": "ir",
      "audio": "assets/audios/83.去",
      "trazo": "https://www.strokeorder.com/assets/bishun/animation/21435.gif"
    },
    {
      "id": 84,
      "hanzi": "热",
      "pinyin": "rè",
      "significado": "calor · caliente",
      "audio": "assets/audios/84.热",
      "trazo": "https://www.strokeorder.com/assets/bishun/animation/28909.gif"
    },
    {
      "id": 85,
      "hanzi": "人",
      "pinyin": "rén",
      "significado": "persona · gente",
      "audio": "assets/audios/85.人",
      "trazo": "https://www.strokeorder.com/assets/bishun/animation/20154.gif"
    },
    {
      "id": 86,
      "hanzi": "认识",
      "pinyin": "rèn shi",
      "significado": "saber · reconocer · estar familiarizado con",
      "audio": "assets/audios/86.认识",
      "trazo": "https://www.strokeorder.com/assets/bishun/animation/35748.gif",
      "trazo2": "https://www.strokeorder.com/assets/bishun/animation/35782.gif"
    },
    {
      "id": 87,
      "hanzi": "三",
      "pinyin": "sān",
      "significado": "tres · 3",
      "audio": "assets/audios/87.三",
      "trazo": "https://www.strokeorder.com/assets/bishun/animation/19977.gif"
    },
    {
      "id": 88,
      "hanzi": "商店",
      "pinyin": "shāng diàn",
      "significado": "tienda",
      "audio": "assets/audios/88.商店",
      "trazo": "https://www.strokeorder.com/assets/bishun/animation/21830.gif",
      "trazo2": "https://www.strokeorder.com/assets/bishun/animation/24215.gif"
    },
    {
      "id": 89,
      "hanzi": "上",
      "pinyin": "shàng",
      "significado": "arriba · sobre · encima de · arriba de · asistir (a clase o reunión) · último (semana/mes/año) · previo · subir a (un lugar) · subir (vehículo)",
      "audio": "assets/audios/89.上",
      "trazo": "https://www.strokeorder.com/assets/bishun/animation/19978.gif"
    },
    {
      "id": 90,
      "hanzi": "上午",
      "pinyin": "shàng wǔ",
      "significado": "la mañana",
      "audio": "assets/audios/90.上午",
      "trazo": "https://www.strokeorder.com/assets/bishun/animation/19978.gif",
      "trazo2": "https://www.strokeorder.com/assets/bishun/animation/21320.gif"
    },
    {
      "id": 91,
      "hanzi": "少",
      "pinyin": "shǎo",
      "significado": "poco",
      "audio": "assets/audios/91.少",
      "trazo": "https://www.strokeorder.com/assets/bishun/animation/23569.gif"
    },
    {
      "id": 92,
      "hanzi": "谁",
      "pinyin": "shéi",
      "significado": "¿quién?",
      "audio": "assets/audios/92.谁",
      "trazo": "https://www.strokeorder.com/assets/bishun/animation/35841.gif"
    },
    {
      "id": 93,
      "hanzi": "什么",
      "pinyin": "shén me",
      "significado": "¿qué? · algo",
      "audio": "assets/audios/93.什么",
      "trazo": "https://www.strokeorder.com/assets/bishun/animation/20160.gif",
      "trazo2": "https://www.strokeorder.com/assets/bishun/animation/20040.gif"
    },
    {
      "id": 94,
      "hanzi": "十",
      "pinyin": "shí",
      "significado": "diez · 10",
      "audio": "assets/audios/94.十",
      "trazo": "https://www.strokeorder.com/assets/bishun/animation/21313.gif"
    },
    {
      "id": 95,
      "hanzi": "时候",
      "pinyin": "shí hou",
      "significado": "momento · período de tiempo",
      "audio": "assets/audios/95.时候",
      "trazo": "https://www.strokeorder.com/assets/bishun/animation/26102.gif",
      "trazo2": "https://www.strokeorder.com/assets/bishun/animation/20505.gif"
    },
    {
      "id": 96,
      "hanzi": "是",
      "pinyin": "shì",
      "significado": "ser · si",
      "audio": "assets/audios/96.是",
      "trazo": "https://www.strokeorder.com/assets/bishun/animation/26159.gif"
    },
    {
      "id": 97,
      "hanzi": "书",
      "pinyin": "shū",
      "significado": "libro",
      "audio": "assets/audios/97.书",
      "trazo": "https://www.strokeorder.com/assets/bishun/animation/20070.gif"
    },
    {
      "id": 98,
      "hanzi": "水",
      "pinyin": "shuǐ",
      "significado": "agua",
      "audio": "assets/audios/98.水",
      "trazo": "https://www.strokeorder.com/assets/bishun/animation/27700.gif"
    },
    {
      "id": 99,
      "hanzi": "水果",
      "pinyin": "shuǐguǒ",
      "significado": "fruta",
      "audio": "assets/audios/99.水果",
      "trazo": "https://www.strokeorder.com/assets/bishun/animation/27700.gif",
      "trazo2": "https://www.strokeorder.com/assets/bishun/animation/26524.gif"
    },
    {
      "id": 100,
      "hanzi": "睡觉",
      "pinyin": "shuì jiào",
      "significado": "dormir",
      "audio": "assets/audios/100.睡觉",
      "trazo": "https://www.strokeorder.com/assets/bishun/animation/30561.gif",
      "trazo2": "https://www.strokeorder.com/assets/bishun/animation/35273.gif"
    },
    {
      "id": 101,
      "hanzi": "说",
      "pinyin": "shuō",
      "significado": "hablar · decir · explicar · regañar",
      "audio": "assets/audios/101.说",
      "trazo": "https://www.strokeorder.com/assets/bishun/animation/35828.gif"
    },
    {
      "id": 102,
      "hanzi": "四",
      "pinyin": "sì",
      "significado": "cuatro · 4",
      "audio": "assets/audios/102.四",
      "trazo": "https://www.strokeorder.com/assets/bishun/animation/22235.gif"
    },
    {
      "id": 103,
      "hanzi": "岁",
      "pinyin": "suì",
      "significado": "años (de edad)",
      "audio": "assets/audios/103.岁",
      "trazo": "https://www.strokeorder.com/assets/bishun/animation/23681.gif"
    },
    {
      "id": 104,
      "hanzi": "他",
      "pinyin": "tā",
      "significado": "él",
      "audio": "assets/audios/104.他",
      "trazo": "https://www.strokeorder.com/assets/bishun/animation/20182.gif"
    },
    {
      "id": 105,
      "hanzi": "她",
      "pinyin": "tā",
      "significado": "ella",
      "audio": "assets/audios/105.她",
      "trazo": "https://www.strokeorder.com/assets/bishun/animation/22905.gif"
    },
    {
      "id": 106,
      "hanzi": "太",
      "pinyin": "tài",
      "significado": "demasiado · excesivamente",
      "audio": "assets/audios/106.太",
      "trazo": "https://www.strokeorder.com/assets/bishun/animation/22826.gif"
    },
    {
      "id": 107,
      "hanzi": "天气",
      "pinyin": "tiān qì",
      "significado": "tiempo (clima)",
      "audio": "assets/audios/107.天气",
      "trazo": "https://www.strokeorder.com/assets/bishun/animation/22825.gif",
      "trazo2": "https://www.strokeorder.com/assets/bishun/animation/27668.gif"
    },
    {
      "id": 108,
      "hanzi": "听",
      "pinyin": "tīng",
      "significado": "escuchar",
      "audio": "assets/audios/108.听",
      "trazo": "https://www.strokeorder.com/assets/bishun/animation/21548.gif"
    },
    {
      "id": 109,
      "hanzi": "同学",
      "pinyin": "tóng xué",
      "significado": "compañero de clase",
      "audio": "assets/audios/109.同学",
      "trazo": "https://www.strokeorder.com/assets/bishun/animation/21516.gif",
      "trazo2": "https://www.strokeorder.com/assets/bishun/animation/23398.gif"
    },
    {
      "id": 110,
      "hanzi": "喂",
      "pinyin": "wèi",
      "significado": "¡oye! · alimentar (un animal, un bebé)",
      "audio": "assets/audios/110.喂",
      "trazo": "https://www.strokeorder.com/assets/bishun/animation/21890.gif"
    },
    {
      "id": 111,
      "hanzi": "我",
      "pinyin": "wǒ",
      "significado": "yo · mi · mío",
      "audio": "assets/audios/111.我",
      "trazo": "https://www.strokeorder.com/assets/bishun/animation/25105.gif"
    },
    {
      "id": 112,
      "hanzi": "我们",
      "pinyin": "wǒ men",
      "significado": "nosotros · nuestro",
      "audio": "assets/audios/112.我们",
      "trazo": "https://www.strokeorder.com/assets/bishun/animation/25105.gif",
      "trazo2": "https://www.strokeorder.com/assets/bishun/animation/20204.gif"
    },
    {
      "id": 113,
      "hanzi": "五",
      "pinyin": "wǔ",
      "significado": "cinco · 5",
      "audio": "assets/audios/113.五",
      "trazo": "https://www.strokeorder.com/assets/bishun/animation/20116.gif"
    },
    {
      "id": 114,
      "hanzi": "喜欢",
      "pinyin": "xǐ huan",
      "significado": "gustar",
      "audio": "assets/audios/114.喜欢",
      "trazo": "https://www.strokeorder.com/assets/bishun/animation/21916.gif",
      "trazo2": "https://www.strokeorder.com/assets/bishun/animation/27426.gif"
    },
    {
      "id": 115,
      "hanzi": "下",
      "pinyin": "xià",
      "significado": "debajo · más tarde · siguiente",
      "audio": "assets/audios/115.下",
      "trazo": "https://www.strokeorder.com/assets/bishun/animation/19979.gif"
    },
    {
      "id": 116,
      "hanzi": "下午",
      "pinyin": "xià wǔ",
      "significado": "la tarde",
      "audio": "assets/audios/116.下午",
      "trazo": "https://www.strokeorder.com/assets/bishun/animation/19979.gif",
      "trazo2": "https://www.strokeorder.com/assets/bishun/animation/21320.gif"
    },
    {
      "id": 117,
      "hanzi": "下雨",
      "pinyin": "xià yǔ",
      "significado": "llover",
      "audio": "assets/audios/117.下雨",
      "trazo": "https://www.strokeorder.com/assets/bishun/animation/19979.gif",
      "trazo2": "https://www.strokeorder.com/assets/bishun/animation/38632.gif"
    },
    {
      "id": 118,
      "hanzi": "先生",
      "pinyin": "xiān sheng",
      "significado": "señor · marido",
      "audio": "assets/audios/118.先生",
      "trazo": "https://www.strokeorder.com/assets/bishun/animation/20808.gif",
      "trazo2": "https://www.strokeorder.com/assets/bishun/animation/29983.gif"
    },
    {
      "id": 119,
      "hanzi": "现在",
      "pinyin": "xiàn zài",
      "significado": "ahora",
      "audio": "assets/audios/119.现在",
      "trazo": "https://www.strokeorder.com/assets/bishun/animation/29616.gif",
      "trazo2": "https://www.strokeorder.com/assets/bishun/animation/22312.gif"
    },
    {
      "id": 120,
      "hanzi": "想",
      "pinyin": "xiǎng",
      "significado": "querer · pensar · desear",
      "audio": "assets/audios/120.想",
      "trazo": "https://www.strokeorder.com/assets/bishun/animation/24819.gif"
    },
    {
      "id": 121,
      "hanzi": "小",
      "pinyin": "xiǎo",
      "significado": "pequeño · joven",
      "audio": "assets/audios/121.小",
      "trazo": "https://www.strokeorder.com/assets/bishun/animation/23567.gif"
    },
    {
      "id": 122,
      "hanzi": "小姐",
      "pinyin": "xiǎo jie",
      "significado": "señorita · chica",
      "audio": "assets/audios/122.小姐",
      "trazo": "https://www.strokeorder.com/assets/bishun/animation/23567.gif",
      "trazo2": "https://www.strokeorder.com/assets/bishun/animation/22992.gif"
    },
    {
      "id": 123,
      "hanzi": "些",
      "pinyin": "xiē",
      "significado": "algunos",
      "audio": "assets/audios/123.些",
      "trazo": "https://www.strokeorder.com/assets/bishun/animation/20123.gif"
    },
    {
      "id": 124,
      "hanzi": "写",
      "pinyin": "xiě",
      "significado": "escribir",
      "audio": "assets/audios/124.写",
      "trazo": "https://www.strokeorder.com/assets/bishun/animation/20889.gif"
    },
    {
      "id": 125,
      "hanzi": "谢谢",
      "pinyin": "xiè xie",
      "significado": "gracias",
      "audio": "assets/audios/125.谢谢",
      "trazo": "https://www.strokeorder.com/assets/bishun/animation/35874.gif"
    },
    {
      "id": 126,
      "hanzi": "星期",
      "pinyin": "xīng qī",
      "significado": "semana",
      "audio": "assets/audios/126.星期",
      "trazo": "https://www.strokeorder.com/assets/bishun/animation/26143.gif",
      "trazo2": "https://www.strokeorder.com/assets/bishun/animation/26399.gif"
    },
    {
      "id": 127,
      "hanzi": "学生",
      "pinyin": "xué sheng",
      "significado": "estudiante",
      "audio": "assets/audios/127.学生",
      "trazo": "https://www.strokeorder.com/assets/bishun/animation/23398.gif",
      "trazo2": "https://www.strokeorder.com/assets/bishun/animation/29983.gif"
    },
    {
      "id": 128,
      "hanzi": "学习",
      "pinyin": "xué xí",
      "significado": "estudiar; aprender",
      "audio": "assets/audios/128.学习",
      "trazo": "https://www.strokeorder.com/assets/bishun/animation/23398.gif",
      "trazo2": "https://www.strokeorder.com/assets/bishun/animation/20064.gif"
    },
    {
      "id": 129,
      "hanzi": "学校",
      "pinyin": "xué xiào",
      "significado": "escuela",
      "audio": "assets/audios/129.学校",
      "trazo": "https://www.strokeorder.com/assets/bishun/animation/23398.gif",
      "trazo2": "https://www.strokeorder.com/assets/bishun/animation/26657.gif"
    },
    {
      "id": 130,
      "hanzi": "一",
      "pinyin": "yī",
      "significado": "uno · 1",
      "audio": "assets/audios/130.一",
      "trazo": "https://www.strokeorder.com/assets/bishun/animation/19968.gif"
    },
    {
      "id": 131,
      "hanzi": "一点儿",
      "pinyin": "yī diǎn er",
      "significado": "un poco · un poco de · un punto de · variante de 一点",
      "audio": "assets/audios/131.一点儿",
      "trazo": "https://www.strokeorder.com/assets/bishun/animation/19968.gif",
      "trazo2": "https://www.strokeorder.com/assets/bishun/animation/28857.gif",
      "trazo3": "https://www.strokeorder.com/assets/bishun/animation/20799.gif"
    },
    {
      "id": 132,
      "hanzi": "医生",
      "pinyin": "yī shēng",
      "significado": "doctor",
      "audio": "assets/audios/132.医生",
      "trazo": "https://www.strokeorder.com/assets/bishun/animation/21307.gif",
      "trazo2": "https://www.strokeorder.com/assets/bishun/animation/29983.gif"
    },
    {
      "id": 133,
      "hanzi": "医院",
      "pinyin": "yī yuàn",
      "significado": "hospital",
      "audio": "assets/audios/133.医院",
      "trazo": "https://www.strokeorder.com/assets/bishun/animation/21307.gif",
      "trazo2": "https://www.strokeorder.com/assets/bishun/animation/38498.gif"
    },
    {
      "id": 134,
      "hanzi": "衣服",
      "pinyin": "yī fu",
      "significado": "ropa",
      "audio": "assets/audios/134.衣服",
      "trazo": "https://www.strokeorder.com/assets/bishun/animation/34915.gif",
      "trazo2": "https://www.strokeorder.com/assets/bishun/animation/26381.gif"
    },
    {
      "id": 135,
      "hanzi": "椅子",
      "pinyin": "yǐ zi",
      "significado": "silla",
      "audio": "assets/audios/135.椅子",
      "trazo": "https://www.strokeorder.com/assets/bishun/animation/26885.gif",
      "trazo2": "https://www.strokeorder.com/assets/bishun/animation/23376.gif"
    },
    {
      "id": 136,
      "hanzi": "有",
      "pinyin": "yǒu",
      "significado": "tener · haber",
      "audio": "assets/audios/136.有",
      "trazo": "https://www.strokeorder.com/assets/bishun/animation/26377.gif"
    },
    {
      "id": 137,
      "hanzi": "月",
      "pinyin": "yuè",
      "significado": "luna · mes",
      "audio": "assets/audios/137.月",
      "trazo": "https://www.strokeorder.com/assets/bishun/animation/26376.gif"
    },
    {
      "id": 138,
      "hanzi": "再见",
      "pinyin": "zài jiàn",
      "significado": "adiós",
      "audio": "assets/audios/138.再见",
      "trazo": "https://www.strokeorder.com/assets/bishun/animation/20877.gif",
      "trazo2": "https://www.strokeorder.com/assets/bishun/animation/35265.gif"
    },
    {
      "id": 139,
      "hanzi": "在",
      "pinyin": "zài",
      "significado": "estar en",
      "audio": "assets/audios/139.在",
      "trazo": "https://www.strokeorder.com/assets/bishun/animation/22312.gif"
    },
    {
      "id": 140,
      "hanzi": "怎么",
      "pinyin": "zěn me",
      "significado": "¿cómo?",
      "audio": "assets/audios/140.怎么",
      "trazo": "https://www.strokeorder.com/assets/bishun/animation/24590.gif",
      "trazo2": "https://www.strokeorder.com/assets/bishun/animation/20040.gif"
    },
    {
      "id": 141,
      "hanzi": "怎么样",
      "pinyin": "zěn me yàng",
      "significado": "¿cómo está?",
      "audio": "assets/audios/141.怎么样",
      "trazo": "https://www.strokeorder.com/assets/bishun/animation/24590.gif",
      "trazo2": "https://www.strokeorder.com/assets/bishun/animation/20040.gif",
      "trazo3": "https://www.strokeorder.com/assets/bishun/animation/26679.gif"
    },
    {
      "id": 142,
      "hanzi": "这",
      "pinyin": "zhè",
      "significado": "éste · ese",
      "audio": "assets/audios/142.这",
      "trazo": "https://www.strokeorder.com/assets/bishun/animation/36825.gif"
    },
    {
      "id": 143,
      "hanzi": "中国",
      "pinyin": "zhōng guó",
      "significado": "China",
      "audio": "assets/audios/143.中国",
      "trazo": "https://www.strokeorder.com/assets/bishun/animation/20013.gif",
      "trazo2": "https://www.strokeorder.com/assets/bishun/animation/22269.gif"
    },
    {
      "id": 144,
      "hanzi": "中午",
      "pinyin": "zhōng wǔ",
      "significado": "mediodía",
      "audio": "assets/audios/144.中午",
      "trazo": "https://www.strokeorder.com/assets/bishun/animation/20013.gif",
      "trazo2": "https://www.strokeorder.com/assets/bishun/animation/21320.gif"
    },
    {
      "id": 145,
      "hanzi": "住",
      "pinyin": "zhù",
      "significado": "vivir",
      "audio": "assets/audios/145.住",
      "trazo": "https://www.strokeorder.com/assets/bishun/animation/20303.gif"
    },
    {
      "id": 146,
      "hanzi": "桌子",
      "pinyin": "zhuō zi",
      "significado": "mesa",
      "audio": "assets/audios/146.桌子",
      "trazo": "https://www.strokeorder.com/assets/bishun/animation/26700.gif",
      "trazo2": "https://www.strokeorder.com/assets/bishun/animation/23376.gif"
    },
    {
      "id": 147,
      "hanzi": "字",
      "pinyin": "zì",
      "significado": "palabra · carácter chino · símbolo",
      "audio": "assets/audios/147.字",
      "trazo": "https://www.strokeorder.com/assets/bishun/animation/23383.gif"
    },
    {
      "id": 148,
      "hanzi": "昨天",
      "pinyin": "zuó tiān",
      "significado": "ayer",
      "audio": "assets/audios/148.昨天",
      "trazo": "https://www.strokeorder.com/assets/bishun/animation/26152.gif",
      "trazo2": "https://www.strokeorder.com/assets/bishun/animation/22825.gif"
    },
    {
      "id": 149,
      "hanzi": "做",
      "pinyin": "zuò",
      "significado": "hacer",
      "audio": "assets/audios/149.做",
      "trazo": "https://www.strokeorder.com/assets/bishun/animation/20570.gif"
    },
    {
      "id": 150,
      "hanzi": "坐",
      "pinyin": "zuò",
      "significado": "tomar asiento · coger (avión, bus, etc) ",
      "audio": "assets/audios/150.坐",
      "trazo": "https://www.strokeorder.com/assets/bishun/animation/22352.gif"
    }
  ],
  "hsk2": [
    {
      "id": 151,
      "hanzi": "吧",
      "pinyin": "ba",
      "significado": "partícula modal utilizada al final de la oración para indicar consulta, sugerencia, solicitud u orden",
      "audio": "assets/audios/151.吧",
      "trazo": "https://www.strokeorder.com/assets/bishun/animation/21543.gif"
    },
    {
      "id": 152,
      "hanzi": "白",
      "pinyin": "bái",
      "significado": "blanco",
      "audio": "assets/audios/152.白",
      "trazo": "https://www.strokeorder.com/assets/bishun/animation/30333.gif"
    },
    {
      "id": 153,
      "hanzi": "百",
      "pinyin": "bǎi",
      "significado": "cien",
      "audio": "assets/audios/153.百",
      "trazo": "https://www.strokeorder.com/assets/bishun/animation/30334.gif"
    },
    {
      "id": 154,
      "hanzi": "帮助",
      "pinyin": "bāng zhù",
      "significado": "ayuda",
      "audio": "assets/audios/154.帮助",
      "trazo": "https://www.strokeorder.com/assets/bishun/animation/24110.gif",
      "trazo2": "https://www.strokeorder.com/assets/bishun/animation/21161.gif"
    },
    {
      "id": 155,
      "hanzi": "报纸",
      "pinyin": "bào zhǐ",
      "significado": "periódico",
      "audio": "assets/audios/155.报纸",
      "trazo": "https://www.strokeorder.com/assets/bishun/animation/25253.gif",
      "trazo2": "https://www.strokeorder.com/assets/bishun/animation/32440.gif"
    },
    {
      "id": 156,
      "hanzi": "比",
      "pinyin": "bǐ",
      "significado": "partícula para hacer uso de la comparación",
      "audio": "assets/audios/156.比",
      "trazo": "https://www.strokeorder.com/assets/bishun/animation/27604.gif"
    },
    {
      "id": 157,
      "hanzi": "别",
      "pinyin": "bié",
      "significado": "negación · otro · marcharse",
      "audio": "assets/audios/157.别",
      "trazo": "https://www.strokeorder.com/assets/bishun/animation/21035.gif"
    },
    {
      "id": 158,
      "hanzi": "宾馆",
      "pinyin": "bīn guǎn",
      "significado": "hotel",
      "audio": "assets/audios/158.宾馆",
      "trazo": "https://www.strokeorder.com/assets/bishun/animation/23486.gif",
      "trazo2": "https://www.strokeorder.com/assets/bishun/animation/39302.gif"
    },
    {
      "id": 159,
      "hanzi": "长",
      "pinyin": "cháng",
      "significado": "largo · constantemente",
      "audio": "assets/audios/159.长",
      "trazo": "https://www.strokeorder.com/assets/bishun/animation/38271.gif"
    },
    {
      "id": 160,
      "hanzi": "唱歌",
      "pinyin": "chàng gē",
      "significado": "cantar una canción",
      "audio": "assets/audios/160.唱歌",
      "trazo": "https://www.strokeorder.com/assets/bishun/animation/21809.gif",
      "trazo2": "https://www.strokeorder.com/assets/bishun/animation/27468.gif"
    },
    {
      "id": 161,
      "hanzi": "出",
      "pinyin": "chū",
      "significado": "salir · elevar",
      "audio": "assets/audios/161.出",
      "trazo": "https://www.strokeorder.com/assets/bishun/animation/20986.gif"
    },
    {
      "id": 162,
      "hanzi": "穿",
      "pinyin": "chuān",
      "significado": "vestirse · llevar puesto",
      "audio": "assets/audios/162.穿",
      "trazo": "https://www.strokeorder.com/assets/bishun/animation/31359.gif"
    },
    {
      "id": 163,
      "hanzi": "次",
      "pinyin": "cì",
      "significado": "veces · para enumerar · para secuencias",
      "audio": "assets/audios/163.次",
      "trazo": "https://www.strokeorder.com/assets/bishun/animation/27425.gif"
    },
    {
      "id": 164,
      "hanzi": "从",
      "pinyin": "cóng",
      "significado": "desde · nunca (seguido de una negación)",
      "audio": "assets/audios/164.从",
      "trazo": "https://www.strokeorder.com/assets/bishun/animation/20174.gif"
    },
    {
      "id": 165,
      "hanzi": "错",
      "pinyin": "cuò",
      "significado": "falllo · error · incorrecto",
      "audio": "assets/audios/165.错",
      "trazo": "https://www.strokeorder.com/assets/bishun/animation/38169.gif"
    },
    {
      "id": 166,
      "hanzi": "打篮球",
      "pinyin": "dǎ lán qiú",
      "significado": "jugar al baloncesto",
      "audio": "assets/audios/166.打篮球",
      "trazo": "https://www.strokeorder.com/assets/bishun/animation/25171.gif",
      "trazo2": "https://www.strokeorder.com/assets/bishun/animation/31726.gif",
      "trazo3": "https://www.strokeorder.com/assets/bishun/animation/29699.gif"
    },
    {
      "id": 167,
      "hanzi": "大家",
      "pinyin": "dà jiā",
      "significado": "todos",
      "audio": "assets/audios/167.大家",
      "trazo": "https://www.strokeorder.com/assets/bishun/animation/22823.gif",
      "trazo2": "https://www.strokeorder.com/assets/bishun/animation/23478.gif"
    },
    {
      "id": 168,
      "hanzi": "但是",
      "pinyin": "dàn shì",
      "significado": "pero · sin embargo",
      "audio": "assets/audios/168.但是",
      "trazo": "https://www.strokeorder.com/assets/bishun/animation/20294.gif",
      "trazo2": "https://www.strokeorder.com/assets/bishun/animation/26159.gif"
    },
    {
      "id": 169,
      "hanzi": "到",
      "pinyin": "dào",
      "significado": "llegar · hacia/hasta (un lugar) · hasta (un período de tiempo) · ir",
      "audio": "assets/audios/169.到",
      "trazo": "https://www.strokeorder.com/assets/bishun/animation/21040.gif"
    },
    {
      "id": 170,
      "hanzi": "得",
      "pinyin": "de",
      "significado": "partícula estructural utilizada detrás de un verbo/adjetivo como verbo, indica efecto, grado o posibilidad",
      "audio": "assets/audios/170.得",
      "trazo": "https://www.strokeorder.com/assets/bishun/animation/24471.gif"
    },
    {
      "id": 171,
      "hanzi": "等",
      "pinyin": "děng",
      "significado": "etcétera · esperar a · grado · igual que",
      "audio": "assets/audios/171.等",
      "trazo": "https://www.strokeorder.com/assets/bishun/animation/31561.gif"
    },
    {
      "id": 172,
      "hanzi": "弟弟",
      "pinyin": "dì di",
      "significado": "hermano menor",
      "audio": "assets/audios/172.弟弟",
      "trazo": "https://www.strokeorder.com/assets/bishun/animation/24351.gif",
      "trazo2": "https://www.strokeorder.com/assets/bishun/animation/24351.gif"
    },
    {
      "id": 173,
      "hanzi": "第一",
      "pinyin": "dì yī",
      "significado": "primero · número uno",
      "audio": "assets/audios/173.第一",
      "trazo": "https://www.strokeorder.com/assets/bishun/animation/31532.gif",
      "trazo2": "https://www.strokeorder.com/assets/bishun/animation/19968.gif"
    },
    {
      "id": 174,
      "hanzi": "懂",
      "pinyin": "dǒng",
      "significado": "entender · saber",
      "audio": "assets/audios/174.懂",
      "trazo": "https://www.strokeorder.com/assets/bishun/animation/25026.gif"
    },
    {
      "id": 175,
      "hanzi": "对",
      "pinyin": "duì",
      "significado": "correcto · un par · opuesto · responder · contra · para · hacia",
      "audio": "assets/audios/175.对",
      "trazo": "https://www.strokeorder.com/assets/bishun/animation/23545.gif"
    },
    {
      "id": 176,
      "hanzi": "房间",
      "pinyin": "fáng jiān",
      "significado": "habitación",
      "audio": "assets/audios/176.房间",
      "trazo": "https://www.strokeorder.com/assets/bishun/animation/25151.gif",
      "trazo2": "https://www.strokeorder.com/assets/bishun/animation/38388.gif"
    },
    {
      "id": 177,
      "hanzi": "非常",
      "pinyin": "fēi cháng",
      "significado": "mucho · extraordinariamente",
      "audio": "assets/audios/177.非常",
      "trazo": "https://www.strokeorder.com/assets/bishun/animation/38750.gif",
      "trazo2": "https://www.strokeorder.com/assets/bishun/animation/24120.gif"
    },
    {
      "id": 178,
      "hanzi": "服务员",
      "pinyin": "fú wù yuán",
      "significado": "camarero",
      "audio": "assets/audios/178.服务员",
      "trazo": "https://www.strokeorder.com/assets/bishun/animation/26381.gif",
      "trazo2": "https://www.strokeorder.com/assets/bishun/animation/21153.gif",
      "trazo3": "https://www.strokeorder.com/assets/bishun/animation/21592.gif"
    },
    {
      "id": 179,
      "hanzi": "高",
      "pinyin": "gāo",
      "significado": "alto · elevado",
      "audio": "assets/audios/179.高",
      "trazo": "https://www.strokeorder.com/assets/bishun/animation/39640.gif"
    },
    {
      "id": 180,
      "hanzi": "告诉",
      "pinyin": "gào su",
      "significado": "decir · informar · hacer saber",
      "audio": "assets/audios/180.告诉",
      "trazo": "https://www.strokeorder.com/assets/bishun/animation/21578.gif",
      "trazo2": "https://www.strokeorder.com/assets/bishun/animation/35785.gif"
    },
    {
      "id": 181,
      "hanzi": "哥哥",
      "pinyin": "gē ge",
      "significado": "hermano mayor",
      "audio": "assets/audios/181.哥哥",
      "trazo": "https://www.strokeorder.com/assets/bishun/animation/21733.gif",
      "trazo2": "https://www.strokeorder.com/assets/bishun/animation/21733.gif"
    },
    {
      "id": 182,
      "hanzi": "给",
      "pinyin": "gěi",
      "significado": "dar · permitir · para (alguien)",
      "audio": "assets/audios/182.给",
      "trazo": "https://www.strokeorder.com/assets/bishun/animation/32473.gif"
    },
    {
      "id": 183,
      "hanzi": "公共汽车",
      "pinyin": "gōng gòng qì chē",
      "significado": "autobús",
      "audio": "assets/audios/183.公共汽车",
      "trazo": "https://www.strokeorder.com/assets/bishun/animation/20844.gif",
      "trazo2": "https://www.strokeorder.com/assets/bishun/animation/20849.gif",
      "trazo3": "https://www.strokeorder.com/assets/bishun/animation/27773.gif",
      "trazo4": "https://www.strokeorder.com/assets/bishun/animation/36710.gif"
    },
    {
      "id": 184,
      "hanzi": "公司",
      "pinyin": "gōng sī",
      "significado": "compañía · empresa",
      "audio": "assets/audios/184.公司",
      "trazo": "https://www.strokeorder.com/assets/bishun/animation/20844.gif",
      "trazo2": "https://www.strokeorder.com/assets/bishun/animation/21496.gif"
    },
    {
      "id": 185,
      "hanzi": "贵",
      "pinyin": "guì",
      "significado": "caro",
      "audio": "assets/audios/185.贵",
      "trazo": "https://www.strokeorder.com/assets/bishun/animation/36149.gif"
    },
    {
      "id": 186,
      "hanzi": "过",
      "pinyin": "guo",
      "significado": "cruzar · pasar · partícula que indica experiencia pasada",
      "audio": "",
      "trazo": ""
    },
    {
      "id": 187,
      "hanzi": "孩子",
      "pinyin": "hái zi",
      "significado": "niño",
      "audio": "",
      "trazo": ""
    },
    {
      "id": 188,
      "hanzi": "还",
      "pinyin": "hái",
      "significado": "bastante · pasable · además · también · aún · todavía · incluso",
      "audio": "",
      "trazo": ""
    },
    {
      "id": 189,
      "hanzi": "好吃",
      "pinyin": "hǎo chī",
      "significado": "delicioso · sabroso",
      "audio": "",
      "trazo": ""
    },
    {
      "id": 190,
      "hanzi": "黑",
      "pinyin": "hēi",
      "significado": "negro · oscuro",
      "audio": "",
      "trazo": ""
    },
    {
      "id": 191,
      "hanzi": "红",
      "pinyin": "hóng",
      "significado": "rojo · popular",
      "audio": "",
      "trazo": ""
    },
    {
      "id": 192,
      "hanzi": "欢迎",
      "pinyin": "huān yíng",
      "significado": "bienvenido",
      "audio": "",
      "trazo": ""
    },
    {
      "id": 193,
      "hanzi": "火车站",
      "pinyin": "huǒ chē zhàn",
      "significado": "estación de tren",
      "audio": "",
      "trazo": ""
    },
    {
      "id": 194,
      "hanzi": "机场",
      "pinyin": "jī chǎng",
      "significado": "aeropuerto",
      "audio": "",
      "trazo": ""
    },
    {
      "id": 195,
      "hanzi": "鸡蛋",
      "pinyin": "jī dàn",
      "significado": "huevo de gallina",
      "audio": "",
      "trazo": ""
    },
    {
      "id": 196,
      "hanzi": "件",
      "pinyin": "jiàn",
      "significado": "CL: ropa, cosas, eventos.",
      "audio": "",
      "trazo": ""
    },
    {
      "id": 197,
      "hanzi": "教室",
      "pinyin": "jiào shì",
      "significado": "clase · aula · salón de clases",
      "audio": "",
      "trazo": ""
    },
    {
      "id": 198,
      "hanzi": "姐姐",
      "pinyin": "jiě jie",
      "significado": "hermana mayor",
      "audio": "",
      "trazo": ""
    },
    {
      "id": 199,
      "hanzi": "介绍",
      "pinyin": "jiè shào",
      "significado": "presentar · sugerir",
      "audio": "",
      "trazo": ""
    },
    {
      "id": 200,
      "hanzi": "近",
      "pinyin": "jìn",
      "significado": "cerca · cerca de",
      "audio": "",
      "trazo": ""
    },
    {
      "id": 201,
      "hanzi": "进",
      "pinyin": "jìn",
      "significado": "entrar · recibir, admitir (a alguien)",
      "audio": "",
      "trazo": ""
    },
    {
      "id": 202,
      "hanzi": "就",
      "pinyin": "jiù",
      "significado": "utilizado para indicar una conclusión o resolución · aquí mismo · solo · justamente · ya · entonces",
      "audio": "",
      "trazo": ""
    },
    {
      "id": 203,
      "hanzi": "觉得",
      "pinyin": "jué de",
      "significado": "pensar · sentir",
      "audio": "",
      "trazo": ""
    },
    {
      "id": 204,
      "hanzi": "咖啡",
      "pinyin": "kā fēi",
      "significado": "café",
      "audio": "",
      "trazo": ""
    },
    {
      "id": 205,
      "hanzi": "开始",
      "pinyin": "kāi shǐ",
      "significado": "empezar",
      "audio": "",
      "trazo": ""
    },
    {
      "id": 206,
      "hanzi": "考试",
      "pinyin": "kǎo shì",
      "significado": "examen",
      "audio": "",
      "trazo": ""
    },
    {
      "id": 207,
      "hanzi": "可能",
      "pinyin": "kě néng",
      "significado": "posibilidad · posiblemente · quizás",
      "audio": "",
      "trazo": ""
    },
    {
      "id": 208,
      "hanzi": "可以",
      "pinyin": "kě yǐ",
      "significado": "poder · ser capaz de",
      "audio": "",
      "trazo": ""
    },
    {
      "id": 209,
      "hanzi": "课",
      "pinyin": "kè",
      "significado": "lección · curso · asignatura",
      "audio": "",
      "trazo": ""
    },
    {
      "id": 210,
      "hanzi": "快",
      "pinyin": "kuài",
      "significado": "rápido",
      "audio": "",
      "trazo": ""
    },
    {
      "id": 211,
      "hanzi": "快乐",
      "pinyin": "kuài lè",
      "significado": "feliz",
      "audio": "",
      "trazo": ""
    },
    {
      "id": 212,
      "hanzi": "累",
      "pinyin": "lèi",
      "significado": "cansado · llevar a cabo · trabajar duro",
      "audio": "",
      "trazo": ""
    },
    {
      "id": 213,
      "hanzi": "离",
      "pinyin": "lí",
      "significado": "irse · partir desde · hasta",
      "audio": "",
      "trazo": ""
    },
    {
      "id": 214,
      "hanzi": "两",
      "pinyin": "liǎng",
      "significado": "ambos · algunos · unos pocos · dos · peso: 50 gramos",
      "audio": "",
      "trazo": ""
    },
    {
      "id": 215,
      "hanzi": "零",
      "pinyin": "líng",
      "significado": "cero · 0",
      "audio": "",
      "trazo": ""
    },
    {
      "id": 216,
      "hanzi": "路",
      "pinyin": "lù",
      "significado": "carretera · calle · camino",
      "audio": "",
      "trazo": ""
    },
    {
      "id": 217,
      "hanzi": "旅游",
      "pinyin": "lǚ yóu",
      "significado": "viaje · viajar · turismo",
      "audio": "",
      "trazo": ""
    },
    {
      "id": 218,
      "hanzi": "卖",
      "pinyin": "mài",
      "significado": "vender",
      "audio": "",
      "trazo": ""
    },
    {
      "id": 219,
      "hanzi": "慢",
      "pinyin": "màn",
      "significado": "despacio",
      "audio": "",
      "trazo": ""
    },
    {
      "id": 220,
      "hanzi": "忙",
      "pinyin": "máng",
      "significado": "ocupado",
      "audio": "",
      "trazo": ""
    },
    {
      "id": 221,
      "hanzi": "每",
      "pinyin": "měi",
      "significado": "cada",
      "audio": "",
      "trazo": ""
    },
    {
      "id": 222,
      "hanzi": "妹妹",
      "pinyin": "mèi mei",
      "significado": "hermana menor",
      "audio": "",
      "trazo": ""
    },
    {
      "id": 223,
      "hanzi": "门",
      "pinyin": "mén",
      "significado": "puerta",
      "audio": "",
      "trazo": ""
    },
    {
      "id": 224,
      "hanzi": "面条",
      "pinyin": "miàn tiáo",
      "significado": "fideos chinos · tallarines chinos",
      "audio": "",
      "trazo": ""
    },
    {
      "id": 225,
      "hanzi": "男",
      "pinyin": "nán",
      "significado": "masculino",
      "audio": "",
      "trazo": ""
    },
    {
      "id": 226,
      "hanzi": "您",
      "pinyin": "nín",
      "significado": "usted",
      "audio": "",
      "trazo": ""
    },
    {
      "id": 227,
      "hanzi": "牛奶",
      "pinyin": "niú nǎi",
      "significado": "leche de vaca",
      "audio": "",
      "trazo": ""
    },
    {
      "id": 228,
      "hanzi": "女",
      "pinyin": "nǚ",
      "significado": "mujer · hembra · hija",
      "audio": "",
      "trazo": ""
    },
    {
      "id": 229,
      "hanzi": "旁边",
      "pinyin": "páng biān",
      "significado": "al lado",
      "audio": "",
      "trazo": ""
    },
    {
      "id": 230,
      "hanzi": "跑步",
      "pinyin": "pǎo bù",
      "significado": "correr",
      "audio": "",
      "trazo": ""
    },
    {
      "id": 231,
      "hanzi": "便宜",
      "pinyin": "pián yi",
      "significado": "barato",
      "audio": "",
      "trazo": ""
    },
    {
      "id": 232,
      "hanzi": "票",
      "pinyin": "piào",
      "significado": "tiquet · entrada · CL: envios y transacciones de negocios",
      "audio": "",
      "trazo": ""
    },
    {
      "id": 233,
      "hanzi": "妻子",
      "pinyin": "qī zi",
      "significado": "esposa · mujer (esposa)",
      "audio": "",
      "trazo": ""
    },
    {
      "id": 234,
      "hanzi": "起床",
      "pinyin": "qǐ chuáng",
      "significado": "despertarse",
      "audio": "",
      "trazo": ""
    },
    {
      "id": 235,
      "hanzi": "千",
      "pinyin": "qiān",
      "significado": "mil",
      "audio": "",
      "trazo": ""
    },
    {
      "id": 236,
      "hanzi": "铅笔",
      "pinyin": "qiān bǐ",
      "significado": "lápiz",
      "audio": "",
      "trazo": ""
    },
    {
      "id": 237,
      "hanzi": "晴",
      "pinyin": "qíng",
      "significado": "soleado · despejado (cielo)",
      "audio": "",
      "trazo": ""
    },
    {
      "id": 238,
      "hanzi": "去年",
      "pinyin": "qù nián",
      "significado": "año pasado",
      "audio": "",
      "trazo": ""
    },
    {
      "id": 239,
      "hanzi": "让",
      "pinyin": "ràng",
      "significado": "proporcionar · permitir",
      "audio": "",
      "trazo": ""
    },
    {
      "id": 240,
      "hanzi": "日",
      "pinyin": "rì",
      "significado": "día; sol",
      "audio": "",
      "trazo": ""
    },
    {
      "id": 241,
      "hanzi": "上班",
      "pinyin": "shàng bān",
      "significado": "ir a trabajar · empezar a trabajar",
      "audio": "",
      "trazo": ""
    },
    {
      "id": 242,
      "hanzi": "身体",
      "pinyin": "shēn tǐ",
      "significado": "cuerpo · salud",
      "audio": "",
      "trazo": ""
    },
    {
      "id": 243,
      "hanzi": "生病",
      "pinyin": "shēng bìng",
      "significado": "enfermar",
      "audio": "",
      "trazo": ""
    },
    {
      "id": 244,
      "hanzi": "生日",
      "pinyin": "shēng rì",
      "significado": "cumpleaños",
      "audio": "",
      "trazo": ""
    },
    {
      "id": 245,
      "hanzi": "时间",
      "pinyin": "shí jiān",
      "significado": "tiempo · período",
      "audio": "",
      "trazo": ""
    },
    {
      "id": 246,
      "hanzi": "事情",
      "pinyin": "shì qing",
      "significado": "asunto · negocio",
      "audio": "",
      "trazo": ""
    },
    {
      "id": 247,
      "hanzi": "手表",
      "pinyin": "shǒu biǎo",
      "significado": "reloj de muñeca",
      "audio": "",
      "trazo": ""
    },
    {
      "id": 248,
      "hanzi": "手机",
      "pinyin": "shǒu jī",
      "significado": "teléfono móvil",
      "audio": "",
      "trazo": ""
    },
    {
      "id": 249,
      "hanzi": "说话",
      "pinyin": "shuō huà",
      "significado": "hablar",
      "audio": "",
      "trazo": ""
    },
    {
      "id": 250,
      "hanzi": "送",
      "pinyin": "sòng",
      "significado": "regalar · entregar",
      "audio": "",
      "trazo": ""
    },
    {
      "id": 251,
      "hanzi": "虽然",
      "pinyin": "suī rán",
      "significado": "aunque · a pesar de que · incluso si",
      "audio": "",
      "trazo": ""
    },
    {
      "id": 252,
      "hanzi": "所以",
      "pinyin": "suǒ yǐ",
      "significado": "por lo tanto · como resultado · entonces",
      "audio": "",
      "trazo": ""
    },
    {
      "id": 253,
      "hanzi": "它",
      "pinyin": "tā",
      "significado": "pronombre de tercera persona para animales y objetos inanimados",
      "audio": "",
      "trazo": ""
    },
    {
      "id": 254,
      "hanzi": "踢足球",
      "pinyin": "tī zú qiú",
      "significado": "jugar al fútbol",
      "audio": "",
      "trazo": ""
    },
    {
      "id": 255,
      "hanzi": "题",
      "pinyin": "tí",
      "significado": "pregunta · problema · pregunta de examen · inscribirse · mencionar · tema",
      "audio": "",
      "trazo": ""
    },
    {
      "id": 256,
      "hanzi": "跳舞",
      "pinyin": "tiào wǔ",
      "significado": "bailar",
      "audio": "",
      "trazo": ""
    },
    {
      "id": 257,
      "hanzi": "外",
      "pinyin": "wài",
      "significado": "de fuera · extranjero",
      "audio": "",
      "trazo": ""
    },
    {
      "id": 258,
      "hanzi": "完",
      "pinyin": "wán",
      "significado": "finalizar",
      "audio": "",
      "trazo": ""
    },
    {
      "id": 259,
      "hanzi": "玩",
      "pinyin": "wán",
      "significado": "jugar · divertirse",
      "audio": "",
      "trazo": ""
    },
    {
      "id": 260,
      "hanzi": "晚上",
      "pinyin": "wǎn shang",
      "significado": "por la tarde/noche",
      "audio": "",
      "trazo": ""
    },
    {
      "id": 261,
      "hanzi": "往",
      "pinyin": "wǎng",
      "significado": "ir (en una dirección) · hacia · (de un tren) rumbo a · pasado · anterior",
      "audio": "",
      "trazo": ""
    },
    {
      "id": 262,
      "hanzi": "为什么",
      "pinyin": "wèi shén me",
      "significado": "¿por qué?",
      "audio": "",
      "trazo": ""
    },
    {
      "id": 263,
      "hanzi": "问",
      "pinyin": "wèn",
      "significado": "preguntar",
      "audio": "",
      "trazo": ""
    },
    {
      "id": 264,
      "hanzi": "问题",
      "pinyin": "wèn tí",
      "significado": "pregunta · problema · cuestión",
      "audio": "",
      "trazo": ""
    },
    {
      "id": 265,
      "hanzi": "希望",
      "pinyin": "xī wàng",
      "significado": "desear · esperanza",
      "audio": "",
      "trazo": ""
    },
    {
      "id": 266,
      "hanzi": "西瓜",
      "pinyin": "xī guā",
      "significado": "sandía",
      "audio": "",
      "trazo": ""
    },
    {
      "id": 267,
      "hanzi": "洗",
      "pinyin": "xǐ",
      "significado": "lavar · bañarse",
      "audio": "",
      "trazo": ""
    },
    {
      "id": 268,
      "hanzi": "向",
      "pinyin": "xiàng",
      "significado": "hacia · dirección · girar hacia · poco antes",
      "audio": "",
      "trazo": ""
    },
    {
      "id": 269,
      "hanzi": "小时",
      "pinyin": "xiǎo shí",
      "significado": "hora",
      "audio": "",
      "trazo": ""
    },
    {
      "id": 270,
      "hanzi": "笑",
      "pinyin": "xiào",
      "significado": "reir · sonreir",
      "audio": "",
      "trazo": ""
    },
    {
      "id": 271,
      "hanzi": "新",
      "pinyin": "xīn",
      "significado": "nuevo",
      "audio": "",
      "trazo": ""
    },
    {
      "id": 272,
      "hanzi": "姓",
      "pinyin": "xìng",
      "significado": "apellido",
      "audio": "",
      "trazo": ""
    },
    {
      "id": 273,
      "hanzi": "休息",
      "pinyin": "xiū xi",
      "significado": "descansar · descanso",
      "audio": "",
      "trazo": ""
    },
    {
      "id": 274,
      "hanzi": "雪",
      "pinyin": "xuě",
      "significado": "nieve",
      "audio": "",
      "trazo": ""
    },
    {
      "id": 275,
      "hanzi": "颜色",
      "pinyin": "yán sè",
      "significado": "color",
      "audio": "",
      "trazo": ""
    },
    {
      "id": 276,
      "hanzi": "眼睛",
      "pinyin": "yǎn jing",
      "significado": "ojos",
      "audio": "",
      "trazo": ""
    },
    {
      "id": 277,
      "hanzi": "羊肉",
      "pinyin": "yáng ròu",
      "significado": "carne de cordero · carne de cabra",
      "audio": "",
      "trazo": ""
    },
    {
      "id": 278,
      "hanzi": "药",
      "pinyin": "yào",
      "significado": "medicina · cura",
      "audio": "",
      "trazo": ""
    },
    {
      "id": 279,
      "hanzi": "要",
      "pinyin": "yào",
      "significado": "importante · querer · quisiera · poder · deber",
      "audio": "",
      "trazo": ""
    },
    {
      "id": 280,
      "hanzi": "也",
      "pinyin": "yě",
      "significado": "también",
      "audio": "",
      "trazo": ""
    },
    {
      "id": 281,
      "hanzi": "一下",
      "pinyin": "yī xià",
      "significado": "utilizado tras un verbo para indicar un acto o un intento · hacer algo (para darle una oportunidad) · una vez · en un rato · de repente · todo de una vez",
      "audio": "",
      "trazo": ""
    },
    {
      "id": 282,
      "hanzi": "已经",
      "pinyin": "yǐ jīng",
      "significado": "ya",
      "audio": "",
      "trazo": ""
    },
    {
      "id": 283,
      "hanzi": "一起",
      "pinyin": "yī qǐ",
      "significado": "juntos · con",
      "audio": "",
      "trazo": ""
    },
    {
      "id": 284,
      "hanzi": "意思",
      "pinyin": "yì si",
      "significado": "deseo · significado · opinión",
      "audio": "",
      "trazo": ""
    },
    {
      "id": 285,
      "hanzi": "阴",
      "pinyin": "yīn",
      "significado": "nublado (cielo)",
      "audio": "",
      "trazo": ""
    },
    {
      "id": 286,
      "hanzi": "因为",
      "pinyin": "yīn wèi",
      "significado": "porque",
      "audio": "",
      "trazo": ""
    },
    {
      "id": 287,
      "hanzi": "游泳",
      "pinyin": "yóu yǒng",
      "significado": "nadar",
      "audio": "",
      "trazo": ""
    },
    {
      "id": 288,
      "hanzi": "右边",
      "pinyin": "yòu biān",
      "significado": "derecha · a la derecha · el lado derecho",
      "audio": "",
      "trazo": ""
    },
    {
      "id": 289,
      "hanzi": "鱼",
      "pinyin": "yú",
      "significado": "pescado",
      "audio": "",
      "trazo": ""
    },
    {
      "id": 290,
      "hanzi": "远",
      "pinyin": "yuǎn",
      "significado": "lejos · distante · remoto",
      "audio": "",
      "trazo": ""
    },
    {
      "id": 291,
      "hanzi": "运动",
      "pinyin": "yùn dòng",
      "significado": "deportes",
      "audio": "",
      "trazo": ""
    },
    {
      "id": 292,
      "hanzi": "再",
      "pinyin": "zài",
      "significado": "de nuevo · entonces · una vez más · otra vez",
      "audio": "",
      "trazo": ""
    },
    {
      "id": 293,
      "hanzi": "早上",
      "pinyin": "zǎo shang",
      "significado": "la mañana · temprano por la mañana",
      "audio": "",
      "trazo": ""
    },
    {
      "id": 294,
      "hanzi": "丈夫",
      "pinyin": "zhàng fu",
      "significado": "marido",
      "audio": "",
      "trazo": ""
    },
    {
      "id": 295,
      "hanzi": "找",
      "pinyin": "zhǎo",
      "significado": "buscar · encontrar · devolver",
      "audio": "",
      "trazo": ""
    },
    {
      "id": 296,
      "hanzi": "着",
      "pinyin": "zhe",
      "significado": "partícula añadida tras un verbo para indicar que la acción todavía se esta realizando · utilizado para indicar un estado",
      "audio": "",
      "trazo": ""
    },
    {
      "id": 297,
      "hanzi": "真",
      "pinyin": "zhēn",
      "significado": "realmente · de veras · genuino",
      "audio": "",
      "trazo": ""
    },
    {
      "id": 298,
      "hanzi": "正在",
      "pinyin": "zhèng zài",
      "significado": "en proceso de · mientras",
      "audio": "",
      "trazo": ""
    },
    {
      "id": 299,
      "hanzi": "知道",
      "pinyin": "zhī dào",
      "significado": "saber",
      "audio": "",
      "trazo": ""
    },
    {
      "id": 300,
      "hanzi": "准备",
      "pinyin": "zhǔn bèi",
      "significado": "preparación · preparar",
      "audio": "",
      "trazo": ""
    },
    {
      "id": 301,
      "hanzi": "走",
      "pinyin": "zǒu",
      "significado": "caminar",
      "audio": "",
      "trazo": ""
    },
    {
      "id": 302,
      "hanzi": "最",
      "pinyin": "zuì",
      "significado": "lo que más · el más · superlativo",
      "audio": "",
      "trazo": ""
    },
    {
      "id": 303,
      "hanzi": "左边",
      "pinyin": "zuǒ biān",
      "significado": "izquierda · a la izquierda · el lado izquierdo",
      "audio": "",
      "trazo": ""
    }
    
  ]
}
